{
  "Meta Data": {
    "1. Information": "Weekly Prices (open, high, low, close) and Volumes",
    "2. Symbol": "MSFT",
    "3. Last Refreshed": "2019-03-21 12:33:22",
    "4. Time Zone": "US/Eastern"
  },
  "Weekly Time Series": {
    "2019-03-21": {
      "1. open": "116.1700",
      "2. high": "118.7900",
      "3. low": "116.0500",
      "4. close": "118.3250",
      "5. volume": "104629124"
    },
    "2019-03-15": {
      "1. open": "110.9900",
      "2. high": "117.2500",
      "3. low": "110.9800",
      "4. close": "115.9100",
      "5. volume": "173532134"
    },
    "2019-03-08": {
      "1. open": "113.0200",
      "2. high": "113.2500",
      "3. low": "108.8000",
      "4. close": "110.5100",
      "5. volume": "111990712"
    },
    "2019-03-01": {
      "1. open": "111.7600",
      "2. high": "113.2400",
      "3. low": "110.8800",
      "4. close": "112.5300",
      "5. volume": "119359497"
    },
    "2019-02-22": {
      "1. open": "107.7900",
      "2. high": "111.2000",
      "3. low": "106.2900",
      "4. close": "110.9700",
      "5. volume": "96472580"
    },
    "2019-02-15": {
      "1. open": "106.2000",
      "2. high": "108.3000",
      "3. low": "104.9650",
      "4. close": "108.2200",
      "5. volume": "110757176"
    },
    "2019-02-08": {
      "1. open": "102.8700",
      "2. high": "107.2700",
      "3. low": "102.7700",
      "4. close": "105.6700",
      "5. volume": "130472196"
    },
    "2019-02-01": {
      "1. open": "106.2600",
      "2. high": "106.4800",
      "3. low": "102.1700",
      "4. close": "102.7800",
      "5. volume": "201611213"
    },
    "2019-01-25": {
      "1. open": "106.7500",
      "2. high": "107.8800",
      "3. low": "104.8600",
      "4. close": "107.1700",
      "5. volume": "112628578"
    }
  }
}